{
    "United States": "United States of America",
    "United Kingdom": "United Kingdom of Great Britain and Northern Ireland",
    "Russia": "Russian Federation",
    "South Korea": "Republic of Korea",
    "Turkey": "Türkiye",
    "Taiwan": "Taiwan Province of China",
    "Vietnam": "Viet Nam",
    "Hong Kong": "China, Hong Kong Special Administrative Region",
    "Czech Republic": "Czechia",
    "Ivory Coast": "Côte d'Ivoire",
    "Tanzania": "United Republic of Tanzania",
    "DR Congo": "Congo",
    "Macau": "China, Macao Special Administrative Region",
    "Palestine": "State of Palestine",
    "Moldova": "Republic of Moldova",
    "Brunei": "Brunei Darussalam",
    "Laos": "Lao People's Democratic Republic",
    "Cape Verde": "Cabo Verde",
    "East Timor": "Timor-Leste",
    "São Tomé and Príncipe": "Sao Tome and Principe"
}